LICENSE
README.md
setup.cfg
setup.py
clpsz/__init__.py
clpsz/__version__.py
clpsz/clpsz_flag.py
clpsz/udatetime.py
clpsz/udir.py
clpsz/ufile.py
clpsz/uprocess.py
clpsz/ustring.py
clpsz_python.egg-info/PKG-INFO
clpsz_python.egg-info/SOURCES.txt
clpsz_python.egg-info/dependency_links.txt
clpsz_python.egg-info/entry_points.txt
clpsz_python.egg-info/requires.txt
clpsz_python.egg-info/top_level.txt