Metadata-Version: 2.1
Name: clpsz-python
Version: 0.0.22
Summary: clpsz's python utils
Home-page: https://github.com/clpsz/clpsz-python
Author: Pengpeng Zuo
Author-email: pengclpsz@gmail.com
License: NO-LICENCE
Platform: UNKNOWN
License-File: LICENSE
